{
	"Edit": "Edit",
	"Delete": "Delete",
	"Copy": "Copy",
	"Done": "Done",
	"View": "View",
	"Car": "Car",
	"Dealership": "Dealership",
	"Company": "Company",
	"Branch": "Branch",
	"Customer": "Customer",
	"Created At": "Created At",
	"State": "Booking State",
	"Are you sure to delete": "Are you sure you want to delete",
	"Cancel": "Cancel",
	"Ok": "Ok",
	"Confirm": "Confirm",
	"Confirm Edit": "Confirm",
	"Add": "Add",
	"Create": "Create",
	"Save": "Save",
	"Close": "Close",
	"Next": "Next",
	"Back": "Back",
	"Empty Selected": "Empty Selected",
	"Reset Password": "Reset Password",
	"Are you sure to reset password": "Are you sure you want to reset password of",
	"Delete account success": "Account Deleted",
	"Are you sure to delete this account": "Are you sure you want to delete this account?",
	"Not found": "Not Found",
	"Logout": "Logout",
	"Inactive": "Inactive",
	"Click or drag file to this area to upload": "Click or drag file to this area to upload",
	"request_upload": "Click or drag file to this area to upload",
	"activate": "Activate",
	"deactivate": "Deactivate",
	"Cost": "Cost",
	"Margin": "Margin",
	"Sell Price": "Sell Price",
	"Are you sure to deactivate": "Are you sure you want to deactivate?",
	"Are you sure to activate": "Are you sure you want to activate?",
	"Changes you made may not be saved.": "Changes you made may not be saved.",
	"Today": "Today",
	"mr": "MR",
	"mrs": "MRS",
	"miss": "MISS",
	"Undo": "Undo",
	"Reset": "Reset",
	"All": "All",
	"Show Inactive": "Show Inactive",
	"Last Updated": "Last Updated",
	"Booking": "Booking",
	"Online": "Online",
	"Walk In": "Walk In",
	"My Profile": "My Profile",
	"This week": "This week",
	"This month": "This month",
	"This year": "This year",
	"Send": "Send",
	"local": "Local",
	"inter": "Inter",
	"all": "All",
	"sell online as soon when approved": "Sell online as soon when approved",
	"Dealership Type": "Dealership Type",
	"placeholder": {
		"selector": {
			"province": "please select province"
		}
	},
	"Preview": "Preview",
	"Select All": "Select All",
	"Unselect All": "Unselect All",
	"Count of car online": "Count of car online",
	"Count of car approved": "Count of car approved",
	"Province": "Province",
	"See all cars": "See all cars",
	"Dealers have car less than 50 percent": "Dealers have car less than 50%",
	"Online car percentage is calculated from the number of approved cars": "Online car percentage is calculated from the number of approved cars.",
	"Search": "Search",
	"Selected": "Selected",
	"Select": "Select",
	"Weekdays": "Weekdays",
	"Weekend": "Weekend",
	"Everyday": "Everyday",
	"Clear": "Clear"
}
