{
  "Car trim": "รุ่นย่อย",
  "Create car trim": "สร้างรุ่นย่อย",
  "Update car trim": "แก้ไขรุ่นย่อย",
  "Car trim name": "ชื่อรุ่นย่อย",
  "Car Trim Details": "รายละเอียด",
  "Body": "ตัวถัง",
  "Seats": "จำนวนที่นั่ง",
  "Doors": "จำนวนประตู",
  "Transmission": "ระบบเกียร์",
  "Auto": "เกียร์อัตโนมัติ",
  "Manual": "เกียร์กระปุก",
  "Fuel": "ระบบเชื้อเพลิง",
  "Petrol": "เบนซิน",
  "Diesel": "ดีเซล",
  "Electric": "ไฟฟ้า",
  "NGV": "NGV",
  "LPG": "LPG",
  "Drivetrain": "ระบบขับเคลื่อน",
  "Engine Size": "ความจุเครื่องยนต์",
  "Car trim option": "อุปกรณ์อำนวยความสะดวกภายในรถ",
  "Car trim safety": "อุปกรณ์ด้านความปลอดภัย",
  "OK": "สร้าง",
  "Save": "บันทึก",
  "Cancel": "ยกเลิก",
  "Delete": "ลบ"
}